toprompt/__init__.py
toprompt/cli_types.py
toprompt/dataclass_types.py
toprompt/fastapi_types.py
toprompt/llmling_types.py
toprompt/py.typed
toprompt/sqlite_types.py
toprompt/sqlmodel_types.py
toprompt/to_prompt.py
toprompt-1.0.0.dist-info/WHEEL
toprompt-1.0.0.dist-info/METADATA
toprompt-1.0.0.dist-info/RECORD
