Metadata-Version: 2.3
Name: toprompt
Version: 1.0.0
Summary: Convert python objects to LLM-friendly descriptions
Keywords: 
Author: Philipp Temminghoff
Author-email: Philipp Temminghoff <philipptemminghoff@googlemail.com>
License: MIT License
Classifier: Development Status :: 4 - Beta
Classifier: Framework :: Pydantic
Classifier: Framework :: Pydantic :: 2
Classifier: Intended Audience :: Developers
Classifier: Operating System :: OS Independent
Classifier: Programming Language :: Python :: 3
Classifier: Programming Language :: Python :: 3 :: Only
Classifier: Programming Language :: Python :: 3.12
Classifier: Programming Language :: Python :: 3.13
Classifier: Programming Language :: Python :: 3.14
Classifier: Topic :: Documentation
Classifier: Topic :: Software Development
Classifier: Topic :: Utilities
Classifier: Typing :: Typed
Requires-Dist: clinspector>=0.2.0
Requires-Dist: fieldz>=0.1.0
Requires-Dist: jinjarope>=0.16.0
Requires-Dist: pydantic
Requires-Dist: sqlmodel>=0.0.22
Requires-Python: >=3.13
Project-URL: Code coverage, https://app.codecov.io/gh/phil65/toprompt
Project-URL: Discussions, https://github.com/phil65/toprompt/discussions
Project-URL: Documentation, https://phil65.github.io/toprompt/
Project-URL: Issues, https://github.com/phil65/toprompt/issues
Project-URL: Source, https://github.com/phil65/toprompt
